{
	"format_version": "1.16.0",
	"minecraft:entity": {
		"description": {
			"identifier": "tgm:warp",
			"is_spawnable": false,
			"is_summonable": true,
			"is_experimental": false
		},
		"components": {
			"minecraft:nameable": {},
			"minecraft:fire_immune": {},
			"minecraft:type_family": {
				"family": [
					"inanimate",
					"warp"
				]
			},
			"minecraft:breathable": {
				"breathes_air": true,
				"breathes_solids": true,
				"breathes_water": true,
				"breathes_lava": true
			},
			"minecraft:tick_world": {
				"never_despawn": true,
				"radius": 1
			},
			"minecraft:damage_sensor": {
				"triggers": {
					"cause": "all",
					"deals_damage": false
				}
			},
			"minecraft:collision_box": {
				"width": 0.4,
				"height": 0.4
			},
			"minecraft:knockback_resistance": {
				"value": 1
			},
			"minecraft:persistent": {},
			"minecraft:pushable": {
				"is_pushable": false,
				"is_pushable_by_piston": false
			},
			"minecraft:physics": {
				"has_gravity": false,
				"has_collision": false
			},
			"minecraft:conditional_bandwidth_optimization": {}
		}
	}
}